svm_label_ranking/__init__.py
svm_label_ranking/arff.py
svm_label_ranking/create_H_matrix_disk_memory.py
svm_label_ranking/crossvalidation_svmlr.py
svm_label_ranking/model.py
svm_label_ranking/svmlr_frankwolfe.py
svm_label_ranking/svmlr_qp.py
svm_label_ranking/tools.py
svm_label_ranking-0.0.2.dist-info/LICENSE.md
svm_label_ranking-0.0.2.dist-info/METADATA
svm_label_ranking-0.0.2.dist-info/WHEEL
svm_label_ranking-0.0.2.dist-info/top_level.txt
svm_label_ranking-0.0.2.dist-info/RECORD
