Metadata-Version: 2.1
Name: svm-label-ranking
Version: 0.0.2
Summary: SVM Label Ranking problem
Home-page: https://github.com/salmuz/svm-label-ranking
Author: Yonatan-Carlos Carranza-Alarcon
Author-email: salmuz@gmail.com
License: BSD
Download-URL: https://github.com/salmuz/svm-label-ranking/tarball/0.0.2
Keywords: SVM,Label Ranking
Platform: UNKNOWN
Classifier: Development Status :: 3 - Alpha
Classifier: Intended Audience :: Developers
Classifier: Programming Language :: Python :: 3
Requires-Dist: ttictoc
Requires-Dist: scipy
Requires-Dist: cvxopt
Requires-Dist: numpy
Requires-Dist: sphinx
Requires-Dist: sphinx-rtd-theme
Requires-Dist: nose
Requires-Dist: coverage
Requires-Dist: pypi-publisher
